odoo/addons/mail_history_mark_unread/README.rst
odoo/addons/mail_history_mark_unread/__init__.py
odoo/addons/mail_history_mark_unread/__manifest__.py
odoo/addons/mail_history_mark_unread/i18n/es.po
odoo/addons/mail_history_mark_unread/i18n/it.po
odoo/addons/mail_history_mark_unread/i18n/mail_history_mark_unread.pot
odoo/addons/mail_history_mark_unread/models/__init__.py
odoo/addons/mail_history_mark_unread/models/mail_message.py
odoo/addons/mail_history_mark_unread/readme/CONTRIBUTORS.md
odoo/addons/mail_history_mark_unread/readme/DESCRIPTION.md
odoo/addons/mail_history_mark_unread/static/description/icon.png
odoo/addons/mail_history_mark_unread/static/description/index.html
odoo/addons/mail_history_mark_unread/static/src/mail_core_web_service_patch.esm.js
odoo/addons/mail_history_mark_unread/static/src/message_actions_patch.esm.js
odoo/addons/mail_history_mark_unread/static/src/message_service_patch.esm.js
odoo/addons/mail_history_mark_unread/tests/__init__.py
odoo/addons/mail_history_mark_unread/tests/test_set_message_undone.py
odoo_addon_mail_history_mark_unread-17.0.1.0.0.4.dist-info/METADATA
odoo_addon_mail_history_mark_unread-17.0.1.0.0.4.dist-info/WHEEL
odoo_addon_mail_history_mark_unread-17.0.1.0.0.4.dist-info/top_level.txt
odoo_addon_mail_history_mark_unread-17.0.1.0.0.4.dist-info/RECORD
